he/__init__.py
he/contexts.py
he/decorators.py
he/file_tools.py
he/handlers.py
he/http_tools.py
he/other.py
he/data/__init__.py
he/data/user_agents.txt
he-2019.3.dist-info/LICENSE.txt
he-2019.3.dist-info/METADATA
he-2019.3.dist-info/WHEEL
he-2019.3.dist-info/entry_points.txt
he-2019.3.dist-info/top_level.txt
he-2019.3.dist-info/RECORD
