Metadata-Version: 2.1
Name: he
Version: 2019.3
Summary: A library of Python helpers.
Home-page: https://github.com/Laurentiu-Andronache/pe
Author: Laurențiu Andronache
Author-email: laurentiu.andronache@trailung.ro
License: UNKNOWN
Project-URL: Bug Reports, https://github.com/Laurentiu-Andronache/he/issues
Project-URL: Say Thanks!, https://saythanks.io/to/Laurentiu-Andronache
Project-URL: Source, https://github.com/Laurentiu-Andronache/he
Keywords: helpers library common useful functions decorators contexts classes
Platform: UNKNOWN
Classifier: Development Status :: 5 - Production/Stable
Classifier: Intended Audience :: Developers
Classifier: Topic :: Software Development :: Libraries
Classifier: License :: OSI Approved :: MIT License
Classifier: Programming Language :: Python :: 3.7
Classifier: Typing :: Typed
Requires-Python: >=3.7
Requires-Dist: requests
Provides-Extra: dev
Requires-Dist: pre-commit ; extra == 'dev'
Requires-Dist: wheel ; extra == 'dev'
Requires-Dist: twine ; extra == 'dev'
Requires-Dist: tox ; extra == 'dev'
Requires-Dist: tox-venv ; extra == 'dev'
Provides-Extra: test
Requires-Dist: pytest ; extra == 'test'
Requires-Dist: pytest-cov ; extra == 'test'
Requires-Dist: pytest-sugar ; extra == 'test'
Requires-Dist: pytest-icdiff ; extra == 'test'
Provides-Extra: tox-manual
Requires-Dist: flake8 ; extra == 'tox-manual'
Requires-Dist: flake8-bugbear ; extra == 'tox-manual'
Requires-Dist: pylint ; extra == 'tox-manual'
Requires-Dist: pytest-xdist ; extra == 'tox-manual'
Requires-Dist: mypy ; extra == 'tox-manual'
Requires-Dist: check-manifest ; extra == 'tox-manual'
